ffpy/__init__.py
ffpy/timer.py
ffpy/timer2.py
FFpy-1.6.2.dist-info/METADATA
FFpy-1.6.2.dist-info/WHEEL
FFpy-1.6.2.dist-info/entry_points.txt
FFpy-1.6.2.dist-info/top_level.txt
FFpy-1.6.2.dist-info/RECORD
