Metadata-Version: 2.1
Name: FFpy
Version: 1.6.2
Summary: Fast Python Script Execution Timer
Home-page: https://github.com/anxkhn/FFpy
Author: Anas Khan
Author-email: anxkhn28@gmail.com
License: GPL-3
Requires-Dist: tabulate
